mammoth/__init__.py
mammoth/cli.py
mammoth/conversion.py
mammoth/document_matchers.py
mammoth/documents.py
mammoth/html_paths.py
mammoth/images.py
mammoth/lists.py
mammoth/options.py
mammoth/raw_text.py
mammoth/results.py
mammoth/transforms.py
mammoth/underline.py
mammoth/zips.py
mammoth/docx/__init__.py
mammoth/docx/body_xml.py
mammoth/docx/comments_xml.py
mammoth/docx/complex_fields.py
mammoth/docx/content_types_xml.py
mammoth/docx/dingbats.py
mammoth/docx/document_xml.py
mammoth/docx/files.py
mammoth/docx/notes_xml.py
mammoth/docx/numbering_xml.py
mammoth/docx/office_xml.py
mammoth/docx/relationships_xml.py
mammoth/docx/style_map.py
mammoth/docx/styles_xml.py
mammoth/docx/uris.py
mammoth/docx/xmlparser.py
mammoth/html/__init__.py
mammoth/html/nodes.py
mammoth/styles/__init__.py
mammoth/styles/parser/__init__.py
mammoth/styles/parser/document_matcher_parser.py
mammoth/styles/parser/errors.py
mammoth/styles/parser/html_path_parser.py
mammoth/styles/parser/style_mapping_parser.py
mammoth/styles/parser/token_iterator.py
mammoth/styles/parser/token_parser.py
mammoth/styles/parser/tokeniser.py
mammoth/writers/__init__.py
mammoth/writers/abc.py
mammoth/writers/html.py
mammoth/writers/markdown.py
mammoth-1.8.0.dist-info/LICENSE
mammoth-1.8.0.dist-info/METADATA
mammoth-1.8.0.dist-info/WHEEL
mammoth-1.8.0.dist-info/entry_points.txt
mammoth-1.8.0.dist-info/top_level.txt
mammoth-1.8.0.dist-info/RECORD
