Metadata-Version: 2.1
Name: mammoth
Version: 1.8.0
Summary: Convert Word documents from docx to simple and clean HTML and Markdown
Home-page: https://github.com/mwilliamson/python-mammoth
Author: Michael Williamson
Author-email: mike@zwobble.org
License: BSD-2-Clause
Keywords: docx word office clean html markdown md
Classifier: Development Status :: 5 - Production/Stable
Classifier: Intended Audience :: Developers
Classifier: License :: OSI Approved :: BSD License
Classifier: Programming Language :: Python
Classifier: Programming Language :: Python :: 3
Classifier: Programming Language :: Python :: 3.7
Classifier: Programming Language :: Python :: 3.8
Classifier: Programming Language :: Python :: 3.9
Classifier: Programming Language :: Python :: 3.10
Classifier: Programming Language :: Python :: 3.11
Classifier: Programming Language :: Python :: 3.12
Requires-Python: >=3.7
License-File: LICENSE
Requires-Dist: cobble<0.2,>=0.1.3
